torchstuff/__init__.py
torchstuff/polygon.py
torchstuff-0.0.1.dist-info/LICENSE
torchstuff-0.0.1.dist-info/METADATA
torchstuff-0.0.1.dist-info/WHEEL
torchstuff-0.0.1.dist-info/top_level.txt
torchstuff-0.0.1.dist-info/zip-safe
torchstuff-0.0.1.dist-info/RECORD
